<?xml version="1.0" encoding="UTF-8"?>

<orgfunctions>
    <function class="ru.runa.wfe.extension.orgfunction.GetActorsByCodesFunction">
    	<param messageKey="orgfunction.param.employeeCode" renderer="ru.runa.af.web.orgfunction.ActorCodeRenderer" />
    </function>
    <function class="ru.runa.wfe.extension.orgfunction.ExecutorByNameFunction">
    	<param messageKey="orgfunction.param.executorName" renderer="ru.runa.af.web.orgfunction.ExecutorNameRenderer" />
    </function>
    <function class="ru.runa.wfe.extension.orgfunction.ExecutorsFromListFunction">
    	<param messageKey="orgfunction.param.listExecutor"  />
    </function>
    <function class="ru.runa.wfe.extension.orgfunction.DemoChiefFunction">
    	<param messageKey="orgfunction.param.employeeCode" renderer="ru.runa.af.web.orgfunction.ActorCodeRenderer" />
    </function>
    <function class="ru.runa.wfe.extension.orgfunction.SQLChiefFunction">
    	<param messageKey="orgfunction.param.employeeCode" renderer="ru.runa.af.web.orgfunction.ActorCodeRenderer" />
    </function>
    <function class="ru.runa.wfe.extension.orgfunction.SQLDirectorFunction">
    	<param messageKey="orgfunction.param.employeeCode" renderer="ru.runa.af.web.orgfunction.ActorCodeRenderer" />
    </function>
    <function class="ru.runa.wfe.extension.orgfunction.AllActorsOrgFunction">
    </function>
</orgfunctions>
